processset/__init__.py
processset/job.py
processset/pool.py
processset/processtype/__init__.py
processset/processtype/process.py
processset-0.0.5.dist-info/LICENSE
processset-0.0.5.dist-info/METADATA
processset-0.0.5.dist-info/WHEEL
processset-0.0.5.dist-info/top_level.txt
processset-0.0.5.dist-info/RECORD
