Metadata-Version: 2.1
Name: processset
Version: 0.0.5
Summary: easy to scale computing processes
Home-page: https://github.com/zhengrenzhe/processset
Author: zhengrenzhe
Author-email: zhengrenzhe.niujie@gmail.com
License: UNKNOWN
Platform: UNKNOWN
Classifier: Programming Language :: Python :: 3 :: Only
Classifier: License :: OSI Approved :: MIT License
